.DS_Store
Imputation/ImputationTools.py
Imputation/__init__.py
Imputation/gain.py
Imputation/utils.py
statistics/__init__.py
Imputation-0.0.3.dist-info/METADATA
Imputation-0.0.3.dist-info/WHEEL
Imputation-0.0.3.dist-info/top_level.txt
Imputation-0.0.3.dist-info/RECORD
