Metadata-Version: 2.1
Name: Imputation
Version: 0.0.3
Summary: This package is used for performing exploratory data analysis
Author: Saisakul Chernbumroong
Author-email: s.chernbumroong@bham.ac.uk
License: UNKNOWN
Keywords: python,first package
Platform: UNKNOWN
Classifier: Development Status :: 3 - Alpha
Classifier: Intended Audience :: Education
Classifier: Programming Language :: Python :: 2
Classifier: Programming Language :: Python :: 3
Classifier: Operating System :: MacOS :: MacOS X
Classifier: Operating System :: Microsoft :: Windows
